{"id":"617172d1-4fd4-4d88-bf19-bdeffdfffb22","map":"AmbroseValley","date":"2026-02-10","duration":1.0,"ticks":101,"rawRangeMs":558,"players":{"a1d360c0-00b5-4622-a137-a9e099c0de46":{"bot":false,"events":[{"px":223.7,"py":105.8,"t":0.0,"e":"Position"},{"px":225.4,"py":125.7,"t":0.0358,"e":"Position"},{"px":227.2,"py":131.0,"t":0.0448,"e":"Position"},{"px":221.8,"py":129.4,"t":0.0556,"e":"Loot"},{"px":228.5,"py":133.5,"t":0.0627,"e":"Position"},{"px":242.0,"py":146.6,"t":0.0717,"e":"Position"},{"px":242.3,"py":146.7,"t":0.0789,"e":"Loot"},{"px":253.0,"py":146.9,"t":0.0896,"e":"Position"},{"px":253.0,"py":146.9,"t":0.0896,"e":"Loot"},{"px":259.5,"py":135.4,"t":0.0986,"e":"Position"},{"px":280.8,"py":144.9,"t":0.1075,"e":"Position"},{"px":282.0,"py":169.1,"t":0.1165,"e":"Position"},{"px":288.9,"py":191.8,"t":0.1254,"e":"Position"},{"px":305.5,"py":196.6,"t":0.1344,"e":"Position"},{"px":320.6,"py":202.6,"t":0.1434,"e":"Position"},{"px":351.3,"py":195.6,"t":0.1523,"e":"Position"},{"px":359.6,"py":196.0,"t":0.1613,"e":"Position"},{"px":372.8,"py":200.1,"t":0.1703,"e":"Position"},{"px":376.1,"py":200.5,"t":0.1792,"e":"Position"},{"px":373.1,"py":204.3,"t":0.1882,"e":"Position"},{"px":377.6,"py":209.2,"t":0.1971,"e":"Position"},{"px":376.1,"py":214.3,"t":0.2061,"e":"Position"},{"px":374.3,"py":222.5,"t":0.2151,"e":"Position"},{"px":371.5,"py":244.0,"t":0.224,"e":"Position"},{"px":375.8,"py":260.4,"t":0.233,"e":"Position"},{"px":370.6,"py":261.6,"t":0.2419,"e":"Position"},{"px":385.0,"py":277.9,"t":0.2599,"e":"Position"},{"px":389.1,"py":273.1,"t":0.2688,"e":"Position"},{"px":390.5,"py":272.0,"t":0.2778,"e":"BotKill"},{"px":391.2,"py":272.0,"t":0.2849,"e":"Loot"},{"px":394.3,"py":276.7,"t":0.2885,"e":"Position"},{"px":402.5,"py":292.0,"t":0.2975,"e":"Position"},{"px":382.6,"py":262.2,"t":0.3154,"e":"Position"},{"px":373.2,"py":258.9,"t":0.3244,"e":"Position"},{"px":368.6,"py":248.9,"t":0.3333,"e":"Position"},{"px":367.2,"py":260.2,"t":0.3513,"e":"Position"},{"px":381.1,"py":265.2,"t":0.3602,"e":"Position"},{"px":384.3,"py":264.9,"t":0.3692,"e":"Position"},{"px":381.8,"py":270.6,"t":0.3781,"e":"Position"},{"px":379.2,"py":285.7,"t":0.3961,"e":"Position"},{"px":378.2,"py":287.1,"t":0.405,"e":"Position"},{"px":378.0,"py":287.4,"t":0.4158,"e":"BotKill"},{"px":396.1,"py":291.5,"t":0.4319,"e":"Position"},{"px":419.1,"py":310.6,"t":0.4409,"e":"Position"},{"px":422.2,"py":311.2,"t":0.4444,"e":"BotKill"},{"px":417.6,"py":292.1,"t":0.4588,"e":"Position"},{"px":421.3,"py":285.0,"t":0.4677,"e":"Position"},{"px":413.0,"py":271.5,"t":0.4767,"e":"Position"},{"px":410.7,"py":268.0,"t":0.4857,"e":"Position"},{"px":397.0,"py":263.3,"t":0.4946,"e":"Position"},{"px":374.7,"py":265.0,"t":0.5036,"e":"Position"},{"px":367.3,"py":260.2,"t":0.5125,"e":"Position"},{"px":380.2,"py":263.3,"t":0.5215,"e":"Position"},{"px":390.4,"py":261.5,"t":0.5305,"e":"Position"},{"px":390.0,"py":265.5,"t":0.5394,"e":"Position"},{"px":382.8,"py":274.2,"t":0.5484,"e":"Position"},{"px":387.2,"py":279.8,"t":0.5573,"e":"Position"},{"px":387.2,"py":279.8,"t":0.5627,"e":"Loot"},{"px":387.2,"py":279.8,"t":0.5627,"e":"Loot"},{"px":382.2,"py":277.1,"t":0.5663,"e":"Position"},{"px":377.5,"py":273.3,"t":0.5753,"e":"Position"},{"px":401.6,"py":264.8,"t":0.6129,"e":"Position"},{"px":398.3,"py":279.4,"t":0.6219,"e":"Position"},{"px":410.0,"py":298.9,"t":0.6308,"e":"Position"},{"px":410.5,"py":296.6,"t":0.6398,"e":"Position"},{"px":412.5,"py":297.0,"t":0.6882,"e":"BotKill"},{"px":425.1,"py":289.3,"t":0.7115,"e":"Position"},{"px":422.0,"py":293.2,"t":0.7186,"e":"BotKill"},{"px":421.2,"py":292.8,"t":0.7222,"e":"Loot"},{"px":421.2,"py":292.8,"t":0.724,"e":"Loot"},{"px":413.4,"py":298.1,"t":0.7276,"e":"Loot"},{"px":413.4,"py":298.1,"t":0.7294,"e":"Loot"},{"px":413.4,"py":298.1,"t":0.7294,"e":"Position"},{"px":428.6,"py":317.3,"t":0.7366,"e":"Loot"},{"px":428.6,"py":317.3,"t":0.7384,"e":"Loot"},{"px":428.6,"py":317.3,"t":0.7384,"e":"Position"},{"px":436.9,"py":322.8,"t":0.7419,"e":"Loot"},{"px":436.9,"py":322.8,"t":0.7419,"e":"Loot"},{"px":430.3,"py":311.3,"t":0.7563,"e":"Loot"},{"px":430.3,"py":311.3,"t":0.7563,"e":"Loot"},{"px":430.3,"py":311.3,"t":0.7563,"e":"Position"},{"px":430.3,"py":311.3,"t":0.7563,"e":"Loot"},{"px":437.9,"py":320.8,"t":0.7652,"e":"Position"},{"px":438.3,"py":321.1,"t":0.7742,"e":"Position"},{"px":440.3,"py":319.4,"t":0.7921,"e":"Position"},{"px":436.9,"py":318.5,"t":0.8011,"e":"Position"},{"px":438.7,"py":317.6,"t":0.81,"e":"Position"},{"px":437.7,"py":318.0,"t":0.819,"e":"Position"},{"px":438.5,"py":328.8,"t":0.828,"e":"Position"},{"px":441.4,"py":361.6,"t":0.8369,"e":"Position"},{"px":443.6,"py":378.1,"t":0.8459,"e":"Position"},{"px":443.6,"py":378.1,"t":0.8477,"e":"Loot"},{"px":446.0,"py":366.6,"t":0.8548,"e":"Position"},{"px":440.1,"py":330.8,"t":0.8638,"e":"Position"},{"px":440.1,"py":318.5,"t":0.8728,"e":"Loot"},{"px":440.1,"py":318.5,"t":0.8728,"e":"Loot"},{"px":440.0,"py":318.4,"t":0.8728,"e":"Position"},{"px":440.0,"py":318.4,"t":0.8746,"e":"Loot"},{"px":440.1,"py":318.5,"t":0.8746,"e":"Loot"},{"px":441.6,"py":331.4,"t":0.9086,"e":"Position"},{"px":446.3,"py":352.4,"t":0.9176,"e":"Position"},{"px":449.0,"py":368.7,"t":0.9283,"e":"Position"},{"px":439.1,"py":393.8,"t":0.9373,"e":"Position"},{"px":434.9,"py":409.6,"t":0.9427,"e":"Loot"},{"px":431.6,"py":410.4,"t":0.9462,"e":"Position"},{"px":403.4,"py":470.8,"t":0.9642,"e":"Position"},{"px":407.2,"py":477.8,"t":0.9695,"e":"Loot"},{"px":405.2,"py":477.1,"t":0.9731,"e":"Position"},{"px":398.0,"py":476.2,"t":0.9821,"e":"Position"},{"px":378.8,"py":485.5,"t":0.991,"e":"Position"},{"px":381.4,"py":490.5,"t":0.9964,"e":"BotKilled"},{"px":381.5,"py":490.7,"t":1.0,"e":"Position"}]}}}