{"id":"7920e645-b13a-4929-b251-93e131ae34a2","map":"AmbroseValley","date":"2026-02-11","duration":1.0,"ticks":144,"rawRangeMs":578,"players":{"6cc3550a-07c0-45ac-bd17-85e986f9be58":{"bot":false,"events":[{"px":261.1,"py":703.6,"t":0.0,"e":"Position"},{"px":261.2,"py":700.2,"t":0.0346,"e":"Position"},{"px":265.7,"py":697.2,"t":0.0433,"e":"Position"},{"px":261.4,"py":694.2,"t":0.0519,"e":"Position"},{"px":257.9,"py":688.9,"t":0.0606,"e":"Position"},{"px":263.8,"py":664.5,"t":0.0692,"e":"Position"},{"px":271.0,"py":633.4,"t":0.0779,"e":"Position"},{"px":271.1,"py":601.2,"t":0.0865,"e":"Position"},{"px":271.7,"py":581.2,"t":0.0952,"e":"Position"},{"px":279.7,"py":556.4,"t":0.1038,"e":"Position"},{"px":291.1,"py":538.5,"t":0.1125,"e":"Position"},{"px":289.2,"py":532.3,"t":0.1211,"e":"BotKill"},{"px":288.0,"py":532.1,"t":0.1211,"e":"Position"},{"px":297.4,"py":534.8,"t":0.128,"e":"Loot"},{"px":297.4,"py":534.8,"t":0.1298,"e":"Loot"},{"px":297.4,"py":534.8,"t":0.1298,"e":"Position"},{"px":293.1,"py":527.6,"t":0.1384,"e":"Position"},{"px":296.9,"py":534.3,"t":0.1557,"e":"Position"},{"px":308.0,"py":531.4,"t":0.1626,"e":"Loot"},{"px":307.2,"py":527.9,"t":0.1644,"e":"Position"},{"px":298.9,"py":527.6,"t":0.173,"e":"Position"},{"px":306.7,"py":533.8,"t":0.1799,"e":"Loot"},{"px":305.8,"py":534.4,"t":0.1817,"e":"Position"},{"px":307.5,"py":537.2,"t":0.1903,"e":"Position"},{"px":328.0,"py":529.6,"t":0.199,"e":"Position"},{"px":329.3,"py":532.1,"t":0.2076,"e":"Position"},{"px":329.6,"py":530.9,"t":0.2145,"e":"BotKill"},{"px":332.5,"py":530.7,"t":0.2163,"e":"Position"},{"px":341.3,"py":516.6,"t":0.2249,"e":"Position"},{"px":347.3,"py":530.0,"t":0.2336,"e":"Position"},{"px":347.3,"py":530.0,"t":0.2353,"e":"Loot"},{"px":347.3,"py":530.0,"t":0.237,"e":"Loot"},{"px":347.3,"py":530.0,"t":0.237,"e":"Loot"},{"px":347.3,"py":530.0,"t":0.2388,"e":"Loot"},{"px":347.3,"py":530.0,"t":0.2405,"e":"Loot"},{"px":347.3,"py":530.0,"t":0.2422,"e":"Loot"},{"px":347.3,"py":530.0,"t":0.2422,"e":"Loot"},{"px":348.0,"py":516.1,"t":0.2509,"e":"Position"},{"px":347.7,"py":488.2,"t":0.2595,"e":"Position"},{"px":358.9,"py":476.8,"t":0.2682,"e":"Position"},{"px":368.5,"py":471.6,"t":0.2751,"e":"BotKill"},{"px":369.3,"py":467.5,"t":0.2768,"e":"Position"},{"px":370.8,"py":455.9,"t":0.282,"e":"Loot"},{"px":369.8,"py":451.9,"t":0.2872,"e":"Position"},{"px":369.6,"py":455.5,"t":0.3097,"e":"Loot"},{"px":367.0,"py":458.4,"t":0.3131,"e":"Position"},{"px":345.2,"py":479.9,"t":0.3218,"e":"Position"},{"px":330.7,"py":495.4,"t":0.3304,"e":"Position"},{"px":337.2,"py":516.4,"t":0.3391,"e":"Position"},{"px":345.0,"py":516.8,"t":0.3426,"e":"BotKill"},{"px":357.1,"py":525.9,"t":0.3651,"e":"Loot"},{"px":357.1,"py":525.9,"t":0.3651,"e":"Position"},{"px":357.6,"py":526.5,"t":0.3668,"e":"Loot"},{"px":355.2,"py":516.2,"t":0.3737,"e":"Position"},{"px":351.0,"py":494.8,"t":0.3824,"e":"Position"},{"px":338.6,"py":477.4,"t":0.391,"e":"Position"},{"px":315.4,"py":464.2,"t":0.3997,"e":"Position"},{"px":315.4,"py":463.4,"t":0.3997,"e":"BotKill"},{"px":313.0,"py":448.6,"t":0.4066,"e":"Loot"},{"px":313.0,"py":448.6,"t":0.4083,"e":"Position"},{"px":313.0,"py":448.6,"t":0.4083,"e":"Loot"},{"px":315.5,"py":429.6,"t":0.417,"e":"Position"},{"px":313.5,"py":432.7,"t":0.4204,"e":"BotKill"},{"px":314.5,"py":429.0,"t":0.4291,"e":"BotKill"},{"px":312.7,"py":427.4,"t":0.4343,"e":"Position"},{"px":312.6,"py":427.6,"t":0.436,"e":"BotKill"},{"px":316.7,"py":428.1,"t":0.4429,"e":"Loot"},{"px":316.7,"py":428.1,"t":0.4429,"e":"Position"},{"px":316.7,"py":428.1,"t":0.4446,"e":"Loot"},{"px":314.8,"py":423.9,"t":0.4481,"e":"Loot"},{"px":314.8,"py":423.9,"t":0.4481,"e":"Loot"},{"px":314.8,"py":423.9,"t":0.4498,"e":"Loot"},{"px":314.8,"py":423.9,"t":0.4516,"e":"Loot"},{"px":313.6,"py":416.8,"t":0.4602,"e":"Position"},{"px":313.8,"py":430.6,"t":0.4689,"e":"Position"},{"px":314.1,"py":442.5,"t":0.4775,"e":"BotKill"},{"px":314.0,"py":442.8,"t":0.4775,"e":"Position"},{"px":311.2,"py":465.0,"t":0.4862,"e":"Position"},{"px":311.1,"py":465.2,"t":0.4913,"e":"Loot"},{"px":295.6,"py":459.8,"t":0.5035,"e":"Position"},{"px":294.0,"py":468.4,"t":0.5121,"e":"Position"},{"px":304.5,"py":479.2,"t":0.5208,"e":"Position"},{"px":333.9,"py":492.6,"t":0.5294,"e":"Position"},{"px":366.4,"py":511.2,"t":0.5381,"e":"Position"},{"px":386.2,"py":522.9,"t":0.5467,"e":"Position"},{"px":385.0,"py":523.4,"t":0.5519,"e":"BotKill"},{"px":383.7,"py":515.3,"t":0.5606,"e":"Loot"},{"px":383.7,"py":515.3,"t":0.5606,"e":"Loot"},{"px":391.3,"py":517.3,"t":0.564,"e":"Position"},{"px":398.1,"py":525.9,"t":0.5709,"e":"BotKill"},{"px":398.7,"py":529.1,"t":0.5727,"e":"Position"},{"px":410.3,"py":543.0,"t":0.5813,"e":"Position"},{"px":410.3,"py":543.0,"t":0.583,"e":"Loot"},{"px":410.3,"py":543.0,"t":0.583,"e":"Loot"},{"px":425.2,"py":525.2,"t":0.59,"e":"Position"},{"px":425.7,"py":526.0,"t":0.6003,"e":"Position"},{"px":428.9,"py":522.5,"t":0.609,"e":"Position"},{"px":433.3,"py":512.7,"t":0.6176,"e":"Position"},{"px":433.4,"py":517.4,"t":0.6263,"e":"Position"},{"px":430.5,"py":519.4,"t":0.6332,"e":"BotKill"},{"px":430.2,"py":519.0,"t":0.6349,"e":"Position"},{"px":432.5,"py":516.4,"t":0.6419,"e":"BotKill"},{"px":432.5,"py":516.4,"t":0.6436,"e":"Position"},{"px":429.7,"py":521.4,"t":0.6505,"e":"BotKill"},{"px":430.0,"py":521.9,"t":0.6522,"e":"Position"},{"px":429.7,"py":519.6,"t":0.6574,"e":"BotKill"},{"px":429.7,"py":522.0,"t":0.6609,"e":"BotKill"},{"px":432.1,"py":517.2,"t":0.6696,"e":"Position"},{"px":430.9,"py":517.4,"t":0.6696,"e":"BotKill"},{"px":424.3,"py":520.5,"t":0.6782,"e":"Position"},{"px":424.1,"py":517.9,"t":0.6799,"e":"BotKill"},{"px":421.6,"py":519.7,"t":0.6869,"e":"Position"},{"px":420.8,"py":520.8,"t":0.6869,"e":"BotKill"},{"px":421.8,"py":522.0,"t":0.6955,"e":"Position"},{"px":423.8,"py":520.7,"t":0.7059,"e":"Loot"},{"px":423.7,"py":521.4,"t":0.7093,"e":"Loot"},{"px":429.5,"py":520.0,"t":0.7128,"e":"Loot"},{"px":429.5,"py":520.0,"t":0.7128,"e":"Position"},{"px":429.5,"py":520.0,"t":0.7128,"e":"Loot"},{"px":435.1,"py":516.0,"t":0.718,"e":"Loot"},{"px":435.1,"py":516.0,"t":0.718,"e":"Loot"},{"px":435.6,"py":516.2,"t":0.7197,"e":"Loot"},{"px":435.6,"py":516.2,"t":0.7197,"e":"Loot"},{"px":436.4,"py":515.6,"t":0.7215,"e":"Position"},{"px":442.7,"py":513.0,"t":0.7249,"e":"Loot"},{"px":442.7,"py":513.0,"t":0.7249,"e":"Loot"},{"px":431.0,"py":510.3,"t":0.7353,"e":"Loot"},{"px":431.0,"py":510.3,"t":0.7353,"e":"Loot"},{"px":431.7,"py":506.5,"t":0.737,"e":"Loot"},{"px":431.7,"py":506.5,"t":0.7388,"e":"Loot"},{"px":431.7,"py":506.5,"t":0.7388,"e":"Position"},{"px":432.4,"py":502.4,"t":0.7439,"e":"Loot"},{"px":432.4,"py":502.4,"t":0.7457,"e":"Loot"},{"px":432.6,"py":497.0,"t":0.7474,"e":"Position"},{"px":434.7,"py":492.9,"t":0.7491,"e":"Loot"},{"px":434.7,"py":492.9,"t":0.7509,"e":"Loot"},{"px":424.5,"py":487.8,"t":0.7543,"e":"Loot"},{"px":424.5,"py":487.8,"t":0.7561,"e":"Position"},{"px":423.9,"py":488.1,"t":0.7803,"e":"Loot"},{"px":416.7,"py":498.7,"t":0.7907,"e":"Position"},{"px":396.5,"py":484.3,"t":0.7993,"e":"Position"},{"px":398.9,"py":482.1,"t":0.8166,"e":"Position"},{"px":400.7,"py":477.6,"t":0.8253,"e":"Position"},{"px":426.2,"py":478.5,"t":0.8339,"e":"Position"},{"px":441.2,"py":462.1,"t":0.8426,"e":"Position"},{"px":463.5,"py":453.8,"t":0.8599,"e":"Position"},{"px":493.9,"py":440.9,"t":0.8685,"e":"Position"},{"px":526.3,"py":444.1,"t":0.8772,"e":"Position"},{"px":554.9,"py":432.8,"t":0.8858,"e":"Position"},{"px":574.8,"py":421.7,"t":0.8945,"e":"Position"},{"px":596.6,"py":424.3,"t":0.9048,"e":"Position"},{"px":614.7,"py":416.1,"t":0.9135,"e":"Position"},{"px":632.0,"py":413.7,"t":0.9221,"e":"Position"},{"px":629.6,"py":418.4,"t":0.9291,"e":"BotKill"},{"px":629.6,"py":418.2,"t":0.9308,"e":"Position"},{"px":608.7,"py":418.1,"t":0.9377,"e":"Loot"},{"px":608.7,"py":418.1,"t":0.9394,"e":"Position"},{"px":610.5,"py":417.1,"t":0.9446,"e":"Loot"},{"px":612.8,"py":417.2,"t":0.9481,"e":"Position"},{"px":639.9,"py":408.8,"t":0.9567,"e":"Position"},{"px":646.7,"py":376.4,"t":0.9654,"e":"Position"},{"px":652.0,"py":345.6,"t":0.974,"e":"Position"},{"px":641.0,"py":327.7,"t":0.9827,"e":"Position"},{"px":651.6,"py":297.8,"t":0.9913,"e":"Position"},{"px":662.6,"py":274.5,"t":1.0,"e":"Position"}]}}}