{"id":"df85107f-d9e8-4c49-bb8e-e75e77ff53ab","map":"AmbroseValley","date":"2026-02-10","duration":1.0,"ticks":46,"rawRangeMs":307,"players":{"b3340cc5-c9fa-4108-b56d-0728bc978a22":{"bot":false,"events":[{"px":61.5,"py":481.2,"t":0.0,"e":"Position"},{"px":51.2,"py":469.7,"t":0.0814,"e":"Position"},{"px":76.2,"py":459.5,"t":0.0977,"e":"Position"},{"px":89.1,"py":445.7,"t":0.114,"e":"Position"},{"px":92.0,"py":437.5,"t":0.1303,"e":"Position"},{"px":97.2,"py":436.1,"t":0.1954,"e":"Position"},{"px":100.4,"py":427.3,"t":0.2117,"e":"Position"},{"px":87.6,"py":422.0,"t":0.228,"e":"Position"},{"px":80.7,"py":419.2,"t":0.2443,"e":"Position"},{"px":87.0,"py":409.4,"t":0.2606,"e":"Position"},{"px":95.5,"py":410.4,"t":0.2769,"e":"Position"},{"px":106.3,"py":403.9,"t":0.2932,"e":"Position"},{"px":106.6,"py":403.9,"t":0.2964,"e":"Loot"},{"px":104.1,"py":409.5,"t":0.3257,"e":"Position"},{"px":104.1,"py":409.5,"t":0.3485,"e":"Loot"},{"px":99.6,"py":408.6,"t":0.3746,"e":"Position"},{"px":99.1,"py":408.0,"t":0.3974,"e":"Loot"},{"px":90.1,"py":407.9,"t":0.4267,"e":"Position"},{"px":90.1,"py":407.9,"t":0.4267,"e":"Loot"},{"px":96.4,"py":409.2,"t":0.4756,"e":"Position"},{"px":96.0,"py":414.3,"t":0.4919,"e":"Position"},{"px":88.2,"py":418.0,"t":0.5081,"e":"Position"},{"px":87.6,"py":417.9,"t":0.5114,"e":"Loot"},{"px":88.1,"py":415.2,"t":0.5244,"e":"Position"},{"px":87.9,"py":414.5,"t":0.5244,"e":"Loot"},{"px":101.5,"py":417.7,"t":0.557,"e":"Position"},{"px":101.5,"py":417.7,"t":0.5635,"e":"Loot"},{"px":100.1,"py":416.2,"t":0.5896,"e":"Position"},{"px":95.7,"py":413.4,"t":0.6059,"e":"Position"},{"px":102.8,"py":404.3,"t":0.6221,"e":"Position"},{"px":102.3,"py":399.1,"t":0.6384,"e":"Position"},{"px":103.1,"py":399.2,"t":0.671,"e":"Position"},{"px":98.6,"py":411.5,"t":0.6873,"e":"Position"},{"px":96.6,"py":413.1,"t":0.7036,"e":"Position"},{"px":87.2,"py":410.1,"t":0.7199,"e":"Position"},{"px":83.8,"py":404.4,"t":0.7362,"e":"Position"},{"px":95.0,"py":399.7,"t":0.7524,"e":"Position"},{"px":95.0,"py":399.7,"t":0.759,"e":"Loot"},{"px":97.4,"py":396.1,"t":0.785,"e":"Position"},{"px":102.7,"py":395.2,"t":0.8013,"e":"Position"},{"px":111.2,"py":399.1,"t":0.8339,"e":"Position"},{"px":107.4,"py":416.0,"t":0.8502,"e":"Position"},{"px":115.8,"py":412.7,"t":0.8664,"e":"Position"},{"px":123.1,"py":417.8,"t":0.899,"e":"Position"},{"px":126.4,"py":416.7,"t":0.9153,"e":"Position"},{"px":141.5,"py":421.9,"t":0.9316,"e":"Position"},{"px":145.8,"py":426.5,"t":0.9805,"e":"Position"},{"px":153.4,"py":431.9,"t":1.0,"e":"Position"}]}}}