{"id":"5f96a041-cd4c-4793-a0e6-e87223f91a94","map":"AmbroseValley","date":"2026-02-10","duration":1.0,"ticks":84,"rawRangeMs":448,"players":{"94d042cb-a0f2-45f3-bdca-42fab73cfef5":{"bot":false,"events":[{"px":682.9,"py":238.5,"t":0.0,"e":"Position"},{"px":675.4,"py":246.6,"t":0.0446,"e":"Position"},{"px":641.9,"py":254.9,"t":0.058,"e":"Position"},{"px":641.9,"py":254.9,"t":0.058,"e":"Loot"},{"px":640.6,"py":256.1,"t":0.0603,"e":"Loot"},{"px":638.5,"py":252.3,"t":0.0692,"e":"Position"},{"px":638.5,"py":252.3,"t":0.0714,"e":"Loot"},{"px":625.4,"py":259.2,"t":0.0804,"e":"Position"},{"px":618.3,"py":296.9,"t":0.0915,"e":"Position"},{"px":601.9,"py":323.2,"t":0.1027,"e":"Position"},{"px":601.9,"py":323.2,"t":0.1049,"e":"Loot"},{"px":601.9,"py":323.2,"t":0.1071,"e":"Loot"},{"px":601.9,"py":323.2,"t":0.1071,"e":"Loot"},{"px":609.0,"py":333.5,"t":0.1138,"e":"Position"},{"px":613.1,"py":370.6,"t":0.125,"e":"Position"},{"px":635.5,"py":386.9,"t":0.1362,"e":"Position"},{"px":636.9,"py":384.8,"t":0.1406,"e":"Loot"},{"px":626.4,"py":391.4,"t":0.1473,"e":"Position"},{"px":624.3,"py":399.9,"t":0.1518,"e":"Loot"},{"px":619.8,"py":403.2,"t":0.1585,"e":"Loot"},{"px":619.8,"py":403.2,"t":0.1585,"e":"Position"},{"px":616.5,"py":407.3,"t":0.1674,"e":"Loot"},{"px":618.8,"py":399.6,"t":0.1696,"e":"Position"},{"px":619.0,"py":394.2,"t":0.1763,"e":"Loot"},{"px":613.4,"py":395.2,"t":0.1808,"e":"Position"},{"px":612.6,"py":391.5,"t":0.192,"e":"Position"},{"px":612.6,"py":390.6,"t":0.192,"e":"Loot"},{"px":617.2,"py":392.1,"t":0.2031,"e":"Position"},{"px":622.7,"py":397.5,"t":0.2143,"e":"Position"},{"px":608.4,"py":390.1,"t":0.2254,"e":"Position"},{"px":614.8,"py":395.2,"t":0.2366,"e":"Position"},{"px":619.3,"py":402.3,"t":0.2478,"e":"Position"},{"px":620.6,"py":407.4,"t":0.2567,"e":"Loot"},{"px":619.3,"py":408.3,"t":0.2589,"e":"Position"},{"px":626.3,"py":400.3,"t":0.2701,"e":"Position"},{"px":627.4,"py":409.1,"t":0.2812,"e":"Position"},{"px":637.5,"py":400.5,"t":0.3036,"e":"Position"},{"px":641.3,"py":409.9,"t":0.3147,"e":"Position"},{"px":639.5,"py":410.3,"t":0.3281,"e":"BotKill"},{"px":632.1,"py":411.7,"t":0.3348,"e":"Loot"},{"px":632.0,"py":408.5,"t":0.3371,"e":"Position"},{"px":631.9,"py":412.3,"t":0.3415,"e":"BotKill"},{"px":631.5,"py":411.6,"t":0.346,"e":"Loot"},{"px":631.2,"py":413.4,"t":0.3482,"e":"Position"},{"px":622.5,"py":411.4,"t":0.3527,"e":"Loot"},{"px":611.2,"py":413.1,"t":0.3594,"e":"Position"},{"px":581.4,"py":416.0,"t":0.3705,"e":"Position"},{"px":581.2,"py":416.0,"t":0.3772,"e":"Loot"},{"px":584.1,"py":419.7,"t":0.3929,"e":"Position"},{"px":574.2,"py":427.4,"t":0.404,"e":"Position"},{"px":561.1,"py":462.4,"t":0.4152,"e":"Position"},{"px":540.1,"py":487.7,"t":0.4263,"e":"Position"},{"px":540.1,"py":487.7,"t":0.433,"e":"Loot"},{"px":529.0,"py":493.2,"t":0.4397,"e":"Position"},{"px":535.0,"py":492.9,"t":0.4509,"e":"Position"},{"px":533.8,"py":493.6,"t":0.4621,"e":"Position"},{"px":527.3,"py":490.3,"t":0.4844,"e":"Position"},{"px":527.8,"py":492.0,"t":0.4955,"e":"Position"},{"px":531.9,"py":491.7,"t":0.5067,"e":"Position"},{"px":528.2,"py":492.7,"t":0.5179,"e":"Position"},{"px":529.8,"py":488.9,"t":0.5513,"e":"Position"},{"px":529.4,"py":492.0,"t":0.5625,"e":"Position"},{"px":535.3,"py":493.2,"t":0.5848,"e":"Position"},{"px":537.2,"py":490.5,"t":0.6071,"e":"Position"},{"px":526.1,"py":491.9,"t":0.6518,"e":"Position"},{"px":524.2,"py":497.4,"t":0.6629,"e":"Position"},{"px":517.3,"py":494.6,"t":0.6741,"e":"Position"},{"px":523.8,"py":492.0,"t":0.6853,"e":"Position"},{"px":528.9,"py":484.6,"t":0.7076,"e":"Position"},{"px":520.3,"py":482.0,"t":0.7299,"e":"Position"},{"px":527.4,"py":481.7,"t":0.7411,"e":"Position"},{"px":520.4,"py":484.7,"t":0.7634,"e":"Position"},{"px":528.2,"py":483.4,"t":0.7857,"e":"Position"},{"px":504.6,"py":464.7,"t":0.8192,"e":"Position"},{"px":494.5,"py":451.6,"t":0.8304,"e":"Position"},{"px":489.0,"py":449.8,"t":0.8438,"e":"Position"},{"px":489.4,"py":445.6,"t":0.8549,"e":"Position"},{"px":499.8,"py":450.6,"t":0.8661,"e":"Position"},{"px":514.6,"py":459.1,"t":0.8772,"e":"Position"},{"px":529.0,"py":471.8,"t":0.8884,"e":"Position"},{"px":529.1,"py":484.7,"t":0.8996,"e":"Position"},{"px":527.7,"py":495.6,"t":0.9107,"e":"Position"},{"px":547.7,"py":522.9,"t":0.9219,"e":"Position"},{"px":549.3,"py":525.8,"t":0.933,"e":"Position"},{"px":536.8,"py":493.5,"t":0.9442,"e":"Position"},{"px":549.9,"py":525.7,"t":0.9888,"e":"Position"},{"px":550.2,"py":523.6,"t":0.9933,"e":"BotKilled"},{"px":550.2,"py":523.6,"t":1.0,"e":"Position"}]}}}