{"id":"f841cfa2-3701-4e26-91f6-99a88fdfe423","map":"AmbroseValley","date":"2026-02-12","duration":1.0,"ticks":153,"rawRangeMs":658,"players":{"10648aa3-b215-4c52-9577-5c5689a08939":{"bot":false,"events":[{"px":222.6,"py":106.0,"t":0.0,"e":"Position"},{"px":237.1,"py":124.5,"t":0.0152,"e":"Position"},{"px":246.6,"py":141.4,"t":0.0228,"e":"Position"},{"px":246.6,"py":141.4,"t":0.0258,"e":"Loot"},{"px":246.6,"py":141.4,"t":0.0258,"e":"Loot"},{"px":246.6,"py":141.4,"t":0.0274,"e":"Loot"},{"px":246.0,"py":144.8,"t":0.0304,"e":"Position"},{"px":243.2,"py":145.6,"t":0.0334,"e":"Loot"},{"px":238.5,"py":149.1,"t":0.038,"e":"Position"},{"px":238.5,"py":149.1,"t":0.038,"e":"Loot"},{"px":238.2,"py":147.6,"t":0.041,"e":"Loot"},{"px":244.5,"py":150.5,"t":0.0456,"e":"Position"},{"px":253.2,"py":146.4,"t":0.0517,"e":"Loot"},{"px":252.0,"py":144.8,"t":0.0532,"e":"Position"},{"px":257.1,"py":146.8,"t":0.0608,"e":"Position"},{"px":254.0,"py":163.7,"t":0.0684,"e":"Position"},{"px":264.3,"py":194.6,"t":0.076,"e":"Position"},{"px":277.9,"py":201.9,"t":0.0836,"e":"Position"},{"px":277.7,"py":202.2,"t":0.0866,"e":"Loot"},{"px":283.4,"py":202.9,"t":0.0912,"e":"Position"},{"px":283.0,"py":232.9,"t":0.0988,"e":"Position"},{"px":304.8,"py":257.8,"t":0.1064,"e":"Position"},{"px":321.9,"py":271.6,"t":0.114,"e":"Position"},{"px":303.5,"py":285.5,"t":0.1216,"e":"Position"},{"px":295.1,"py":313.3,"t":0.1292,"e":"Position"},{"px":292.6,"py":342.8,"t":0.1368,"e":"Position"},{"px":300.6,"py":365.5,"t":0.1444,"e":"Position"},{"px":297.7,"py":377.4,"t":0.152,"e":"Position"},{"px":297.7,"py":377.4,"t":0.155,"e":"Loot"},{"px":305.9,"py":377.1,"t":0.1596,"e":"Position"},{"px":309.5,"py":401.1,"t":0.1672,"e":"Position"},{"px":332.2,"py":397.3,"t":0.1748,"e":"Position"},{"px":342.9,"py":390.2,"t":0.1778,"e":"Loot"},{"px":344.6,"py":386.4,"t":0.1824,"e":"Position"},{"px":350.2,"py":394.8,"t":0.19,"e":"Position"},{"px":353.9,"py":406.3,"t":0.1976,"e":"Position"},{"px":334.2,"py":401.1,"t":0.2052,"e":"Position"},{"px":329.2,"py":398.1,"t":0.2128,"e":"Position"},{"px":329.4,"py":401.7,"t":0.2158,"e":"BotKill"},{"px":330.1,"py":415.9,"t":0.2204,"e":"Position"},{"px":330.1,"py":415.9,"t":0.2219,"e":"Loot"},{"px":330.1,"py":415.9,"t":0.2219,"e":"Loot"},{"px":329.1,"py":419.7,"t":0.228,"e":"Position"},{"px":314.8,"py":425.3,"t":0.2356,"e":"Position"},{"px":313.5,"py":437.4,"t":0.2401,"e":"BotKill"},{"px":317.3,"py":440.6,"t":0.2432,"e":"Position"},{"px":313.9,"py":440.1,"t":0.2538,"e":"Loot"},{"px":313.9,"py":440.1,"t":0.2538,"e":"Loot"},{"px":311.9,"py":441.2,"t":0.2584,"e":"Position"},{"px":308.6,"py":451.4,"t":0.2629,"e":"Loot"},{"px":308.1,"py":451.3,"t":0.2675,"e":"Position"},{"px":309.4,"py":462.9,"t":0.2827,"e":"Position"},{"px":309.4,"py":462.9,"t":0.2872,"e":"Loot"},{"px":295.3,"py":446.1,"t":0.2979,"e":"Position"},{"px":295.5,"py":445.6,"t":0.3009,"e":"Loot"},{"px":286.6,"py":442.8,"t":0.3055,"e":"Position"},{"px":277.9,"py":437.7,"t":0.3131,"e":"Position"},{"px":277.9,"py":437.7,"t":0.3131,"e":"Loot"},{"px":279.5,"py":458.3,"t":0.3207,"e":"Position"},{"px":278.6,"py":483.3,"t":0.3283,"e":"Position"},{"px":284.0,"py":491.7,"t":0.3328,"e":"Loot"},{"px":286.4,"py":492.4,"t":0.3359,"e":"Position"},{"px":294.2,"py":501.7,"t":0.3435,"e":"Position"},{"px":289.7,"py":524.8,"t":0.3511,"e":"Position"},{"px":291.6,"py":525.7,"t":0.3541,"e":"Loot"},{"px":296.6,"py":536.6,"t":0.3587,"e":"Position"},{"px":295.1,"py":538.1,"t":0.3602,"e":"Loot"},{"px":300.7,"py":526.9,"t":0.3663,"e":"Position"},{"px":306.1,"py":538.6,"t":0.3723,"e":"Loot"},{"px":305.6,"py":538.5,"t":0.3739,"e":"Position"},{"px":301.4,"py":538.4,"t":0.3815,"e":"Position"},{"px":289.6,"py":542.9,"t":0.3891,"e":"Position"},{"px":278.0,"py":567.7,"t":0.3967,"e":"Position"},{"px":265.5,"py":593.8,"t":0.4043,"e":"Position"},{"px":256.9,"py":625.9,"t":0.4119,"e":"Position"},{"px":238.1,"py":650.3,"t":0.4195,"e":"Position"},{"px":233.3,"py":657.8,"t":0.4255,"e":"Loot"},{"px":234.4,"py":662.8,"t":0.4271,"e":"Position"},{"px":231.6,"py":688.5,"t":0.4347,"e":"Position"},{"px":227.6,"py":718.0,"t":0.4422,"e":"Position"},{"px":232.4,"py":742.2,"t":0.4498,"e":"Position"},{"px":234.5,"py":745.7,"t":0.4559,"e":"Loot"},{"px":235.4,"py":751.0,"t":0.4574,"e":"Position"},{"px":236.3,"py":767.5,"t":0.465,"e":"Loot"},{"px":236.3,"py":767.5,"t":0.465,"e":"Position"},{"px":258.1,"py":758.4,"t":0.4726,"e":"Position"},{"px":258.5,"py":757.5,"t":0.4802,"e":"Loot"},{"px":281.3,"py":760.5,"t":0.4878,"e":"Position"},{"px":290.2,"py":774.2,"t":0.4954,"e":"Position"},{"px":304.0,"py":796.1,"t":0.503,"e":"Position"},{"px":309.6,"py":814.2,"t":0.5106,"e":"Position"},{"px":306.0,"py":811.8,"t":0.5137,"e":"Loot"},{"px":306.9,"py":828.7,"t":0.5182,"e":"Position"},{"px":319.0,"py":854.8,"t":0.5258,"e":"Position"},{"px":346.3,"py":874.3,"t":0.535,"e":"Position"},{"px":356.2,"py":892.3,"t":0.5426,"e":"Position"},{"px":361.0,"py":894.2,"t":0.5456,"e":"Loot"},{"px":360.9,"py":892.5,"t":0.5502,"e":"Position"},{"px":360.9,"py":892.5,"t":0.5517,"e":"Loot"},{"px":360.9,"py":892.5,"t":0.5517,"e":"Loot"},{"px":360.9,"py":886.4,"t":0.5578,"e":"Position"},{"px":359.2,"py":889.4,"t":0.5593,"e":"Loot"},{"px":365.7,"py":885.3,"t":0.5653,"e":"Position"},{"px":374.4,"py":894.9,"t":0.5684,"e":"Loot"},{"px":373.3,"py":894.8,"t":0.5729,"e":"Position"},{"px":373.3,"py":894.8,"t":0.5836,"e":"Loot"},{"px":371.3,"py":888.8,"t":0.5927,"e":"Loot"},{"px":369.2,"py":891.1,"t":0.5957,"e":"Position"},{"px":365.0,"py":874.1,"t":0.6033,"e":"Position"},{"px":384.1,"py":883.6,"t":0.6109,"e":"Position"},{"px":381.5,"py":893.7,"t":0.6185,"e":"Loot"},{"px":381.5,"py":893.7,"t":0.6185,"e":"Position"},{"px":379.7,"py":901.7,"t":0.6261,"e":"Position"},{"px":348.0,"py":902.7,"t":0.6337,"e":"Position"},{"px":317.3,"py":904.4,"t":0.6413,"e":"Position"},{"px":282.4,"py":903.3,"t":0.6489,"e":"Position"},{"px":258.0,"py":896.0,"t":0.6565,"e":"Position"},{"px":246.3,"py":891.7,"t":0.6641,"e":"Position"},{"px":217.7,"py":880.8,"t":0.6717,"e":"Position"},{"px":219.4,"py":869.0,"t":0.6778,"e":"Loot"},{"px":218.7,"py":869.5,"t":0.6793,"e":"Position"},{"px":204.0,"py":851.5,"t":0.6869,"e":"Loot"},{"px":204.0,"py":851.5,"t":0.6869,"e":"Position"},{"px":204.0,"py":851.5,"t":0.6884,"e":"Loot"},{"px":205.0,"py":848.9,"t":0.6945,"e":"Position"},{"px":196.0,"py":840.9,"t":0.7021,"e":"Position"},{"px":185.6,"py":849.4,"t":0.7173,"e":"Position"},{"px":203.4,"py":848.3,"t":0.7234,"e":"Loot"},{"px":202.5,"py":846.2,"t":0.7249,"e":"Position"},{"px":225.0,"py":838.1,"t":0.7325,"e":"Position"},{"px":257.7,"py":829.3,"t":0.7401,"e":"Position"},{"px":280.0,"py":805.3,"t":0.7477,"e":"Position"},{"px":276.5,"py":780.6,"t":0.7553,"e":"Position"},{"px":293.7,"py":778.1,"t":0.7933,"e":"Position"},{"px":310.6,"py":801.1,"t":0.8009,"e":"Position"},{"px":340.8,"py":808.3,"t":0.81,"e":"Position"},{"px":372.6,"py":795.2,"t":0.8176,"e":"Position"},{"px":394.8,"py":771.4,"t":0.8252,"e":"Position"},{"px":397.0,"py":746.9,"t":0.8328,"e":"Position"},{"px":403.8,"py":711.6,"t":0.8404,"e":"Position"},{"px":413.6,"py":689.0,"t":0.848,"e":"Position"},{"px":428.8,"py":655.6,"t":0.8556,"e":"Position"},{"px":443.1,"py":635.3,"t":0.8632,"e":"Position"},{"px":427.5,"py":654.4,"t":0.8784,"e":"Position"},{"px":429.9,"py":667.2,"t":0.886,"e":"Position"},{"px":443.7,"py":688.5,"t":0.8936,"e":"Position"},{"px":457.3,"py":713.1,"t":0.9012,"e":"Position"},{"px":466.1,"py":738.5,"t":0.9088,"e":"Position"},{"px":451.0,"py":766.0,"t":0.9164,"e":"Position"},{"px":449.8,"py":799.2,"t":0.924,"e":"Position"},{"px":451.2,"py":821.2,"t":0.9316,"e":"Position"},{"px":477.8,"py":837.1,"t":0.9392,"e":"Position"},{"px":489.9,"py":853.6,"t":0.9468,"e":"Position"},{"px":490.6,"py":853.5,"t":0.9498,"e":"Loot"},{"px":479.9,"py":861.5,"t":0.9544,"e":"Position"},{"px":475.9,"py":862.4,"t":0.9559,"e":"Loot"},{"px":473.7,"py":851.3,"t":0.962,"e":"Position"},{"px":479.8,"py":860.0,"t":0.9696,"e":"Position"},{"px":470.1,"py":853.0,"t":0.9772,"e":"Position"},{"px":488.8,"py":851.6,"t":0.9848,"e":"Position"},{"px":493.9,"py":844.4,"t":0.9924,"e":"Position"},{"px":500.1,"py":837.1,"t":1.0,"e":"Position"}]}}}