{"id":"bb0b75b0-3910-41fc-a545-bd14c64767d2","map":"AmbroseValley","date":"2026-02-10","duration":1.0,"ticks":120,"rawRangeMs":764,"players":{"cfa03e9f-81f6-41ef-a0fa-30c7e830f4ed":{"bot":false,"events":[{"px":692.6,"py":242.2,"t":0.0,"e":"Position"},{"px":685.0,"py":255.3,"t":0.0982,"e":"Position"},{"px":683.8,"py":258.6,"t":0.1191,"e":"Position"},{"px":685.2,"py":279.5,"t":0.1257,"e":"Position"},{"px":690.7,"py":314.3,"t":0.1322,"e":"Position"},{"px":678.3,"py":346.5,"t":0.1387,"e":"Position"},{"px":647.9,"py":349.6,"t":0.1453,"e":"Position"},{"px":634.2,"py":356.2,"t":0.1518,"e":"Position"},{"px":625.3,"py":379.0,"t":0.1584,"e":"Position"},{"px":619.0,"py":404.7,"t":0.1649,"e":"Position"},{"px":601.9,"py":397.1,"t":0.1715,"e":"Position"},{"px":578.4,"py":397.1,"t":0.178,"e":"Position"},{"px":570.6,"py":406.2,"t":0.1846,"e":"Position"},{"px":565.3,"py":418.8,"t":0.1911,"e":"Position"},{"px":563.5,"py":416.5,"t":0.195,"e":"BotKill"},{"px":565.4,"py":409.8,"t":0.1976,"e":"Position"},{"px":589.3,"py":399.4,"t":0.2042,"e":"Position"},{"px":606.0,"py":390.6,"t":0.2107,"e":"Position"},{"px":612.5,"py":390.6,"t":0.2134,"e":"Loot"},{"px":612.0,"py":391.4,"t":0.2173,"e":"Position"},{"px":618.0,"py":393.8,"t":0.2238,"e":"Position"},{"px":624.6,"py":399.9,"t":0.2264,"e":"Loot"},{"px":619.0,"py":403.7,"t":0.2304,"e":"Loot"},{"px":619.0,"py":403.7,"t":0.2304,"e":"Position"},{"px":612.6,"py":411.0,"t":0.2369,"e":"Position"},{"px":588.0,"py":412.2,"t":0.2435,"e":"Position"},{"px":586.6,"py":411.4,"t":0.2474,"e":"BotKill"},{"px":587.7,"py":409.2,"t":0.25,"e":"Position"},{"px":586.2,"py":398.5,"t":0.2539,"e":"Loot"},{"px":586.2,"py":398.5,"t":0.2552,"e":"Loot"},{"px":585.3,"py":402.2,"t":0.2565,"e":"Position"},{"px":582.1,"py":409.0,"t":0.2631,"e":"Position"},{"px":587.1,"py":399.9,"t":0.2827,"e":"Position"},{"px":563.2,"py":412.1,"t":0.2893,"e":"Position"},{"px":554.8,"py":411.3,"t":0.2932,"e":"Loot"},{"px":554.8,"py":411.3,"t":0.2932,"e":"Loot"},{"px":554.8,"py":411.3,"t":0.2945,"e":"Loot"},{"px":554.1,"py":414.5,"t":0.2958,"e":"Position"},{"px":535.2,"py":428.6,"t":0.3024,"e":"Position"},{"px":535.6,"py":431.0,"t":0.3089,"e":"Position"},{"px":537.2,"py":434.2,"t":0.3154,"e":"BotKill"},{"px":537.7,"py":435.5,"t":0.3154,"e":"Position"},{"px":528.8,"py":419.7,"t":0.3207,"e":"Loot"},{"px":529.0,"py":419.9,"t":0.322,"e":"Loot"},{"px":529.0,"py":419.9,"t":0.322,"e":"Position"},{"px":516.5,"py":434.8,"t":0.3285,"e":"Position"},{"px":508.5,"py":434.7,"t":0.3364,"e":"Position"},{"px":506.9,"py":429.3,"t":0.3429,"e":"Position"},{"px":502.4,"py":428.3,"t":0.3495,"e":"Position"},{"px":502.5,"py":423.8,"t":0.3521,"e":"BotKill"},{"px":507.5,"py":429.5,"t":0.3547,"e":"Loot"},{"px":507.4,"py":429.4,"t":0.356,"e":"Position"},{"px":507.4,"py":429.4,"t":0.356,"e":"Loot"},{"px":510.0,"py":450.5,"t":0.3626,"e":"Position"},{"px":514.9,"py":464.1,"t":0.3691,"e":"Position"},{"px":529.1,"py":482.3,"t":0.3757,"e":"Position"},{"px":529.7,"py":488.1,"t":0.3953,"e":"Position"},{"px":531.4,"py":484.1,"t":0.4018,"e":"Position"},{"px":536.2,"py":490.0,"t":0.4149,"e":"Position"},{"px":533.4,"py":496.6,"t":0.4215,"e":"Position"},{"px":501.4,"py":486.8,"t":0.428,"e":"Position"},{"px":472.9,"py":474.7,"t":0.4346,"e":"Position"},{"px":478.3,"py":453.7,"t":0.4411,"e":"Position"},{"px":505.4,"py":433.8,"t":0.4476,"e":"Position"},{"px":528.7,"py":420.7,"t":0.4542,"e":"Position"},{"px":554.5,"py":411.4,"t":0.4607,"e":"Position"},{"px":570.4,"py":429.1,"t":0.4673,"e":"Position"},{"px":564.3,"py":452.5,"t":0.4738,"e":"Position"},{"px":550.0,"py":467.2,"t":0.4804,"e":"Position"},{"px":568.7,"py":479.5,"t":0.4869,"e":"Position"},{"px":590.7,"py":491.3,"t":0.4935,"e":"Position"},{"px":597.5,"py":516.9,"t":0.5,"e":"Position"},{"px":613.7,"py":540.5,"t":0.5065,"e":"Position"},{"px":608.5,"py":569.6,"t":0.5131,"e":"Position"},{"px":601.7,"py":572.2,"t":0.5196,"e":"Loot"},{"px":601.7,"py":572.2,"t":0.5196,"e":"Position"},{"px":594.9,"py":570.8,"t":0.5262,"e":"Position"},{"px":594.1,"py":571.6,"t":0.5275,"e":"Loot"},{"px":587.8,"py":575.5,"t":0.5301,"e":"Loot"},{"px":591.1,"py":570.5,"t":0.5327,"e":"Position"},{"px":591.7,"py":572.1,"t":0.5353,"e":"Loot"},{"px":591.9,"py":561.3,"t":0.5393,"e":"Loot"},{"px":592.0,"py":561.7,"t":0.5393,"e":"Position"},{"px":593.2,"py":565.0,"t":0.5419,"e":"Loot"},{"px":583.9,"py":567.6,"t":0.5458,"e":"Position"},{"px":584.7,"py":591.7,"t":0.5524,"e":"Position"},{"px":585.1,"py":591.9,"t":0.5537,"e":"Loot"},{"px":582.6,"py":591.3,"t":0.555,"e":"Loot"},{"px":592.5,"py":588.3,"t":0.5576,"e":"Loot"},{"px":593.3,"py":589.8,"t":0.5589,"e":"Position"},{"px":593.3,"py":589.8,"t":0.5602,"e":"Loot"},{"px":579.0,"py":598.2,"t":0.5654,"e":"Position"},{"px":548.4,"py":586.9,"t":0.5733,"e":"Position"},{"px":530.0,"py":574.2,"t":0.5798,"e":"Position"},{"px":530.3,"py":572.0,"t":0.5825,"e":"Loot"},{"px":533.2,"py":562.4,"t":0.5851,"e":"Loot"},{"px":533.2,"py":562.4,"t":0.5864,"e":"Position"},{"px":525.1,"py":551.9,"t":0.5929,"e":"Position"},{"px":523.6,"py":574.0,"t":0.5995,"e":"Position"},{"px":524.7,"py":574.7,"t":0.6008,"e":"Loot"},{"px":522.1,"py":575.6,"t":0.606,"e":"Position"},{"px":526.2,"py":581.9,"t":0.6126,"e":"Position"},{"px":526.2,"py":581.9,"t":0.6126,"e":"Loot"},{"px":530.7,"py":583.2,"t":0.6152,"e":"Loot"},{"px":540.4,"py":582.4,"t":0.6191,"e":"Position"},{"px":557.4,"py":554.1,"t":0.6257,"e":"Position"},{"px":560.6,"py":540.6,"t":0.6322,"e":"Position"},{"px":586.1,"py":535.1,"t":0.6387,"e":"Position"},{"px":616.0,"py":549.2,"t":0.6453,"e":"Position"},{"px":611.4,"py":578.5,"t":0.6518,"e":"Position"},{"px":610.4,"py":583.8,"t":0.6584,"e":"Position"},{"px":599.3,"py":613.1,"t":0.6649,"e":"Position"},{"px":601.7,"py":633.4,"t":0.6715,"e":"Position"},{"px":591.3,"py":629.0,"t":0.678,"e":"Position"},{"px":583.2,"py":635.3,"t":0.6846,"e":"Position"},{"px":581.9,"py":639.6,"t":0.6911,"e":"Position"},{"px":581.6,"py":616.5,"t":0.6976,"e":"Position"},{"px":576.9,"py":588.9,"t":0.7042,"e":"Position"},{"px":562.6,"py":560.5,"t":0.7107,"e":"Position"},{"px":543.6,"py":545.4,"t":0.7173,"e":"Position"},{"px":539.9,"py":544.0,"t":0.7238,"e":"Position"},{"px":540.7,"py":544.8,"t":0.7304,"e":"Position"},{"px":546.1,"py":540.2,"t":0.75,"e":"Position"},{"px":540.3,"py":545.3,"t":0.9215,"e":"Position"},{"px":540.3,"py":545.3,"t":0.9215,"e":"Loot"},{"px":540.3,"py":545.3,"t":0.9228,"e":"Loot"},{"px":546.1,"py":540.3,"t":0.9346,"e":"Position"},{"px":553.4,"py":548.8,"t":0.9673,"e":"Position"},{"px":564.0,"py":552.4,"t":1.0,"e":"Position"}]}}}